{"name":"Jason James","tagline":"","body":"## Jason Charles James\r\n\r\n2723 Cedar Drive\r\nLawrenceville, GA 30043 \r\n770-366-6979\r\n\r\n## EDUCATION\r\n\r\nGeorgia Gwinnett College, Lawrenceville, GA\r\n \tInformation Technology with Software Development Concentration\r\n\tExpected date of graduation:  December 2014\r\nOverall GPA – 3.49, ITEC GPA – 3.60\r\n\r\nGeorgia Perimeter College, Dunwoody, GA\t\t\t\t\t\t\r\nA.S. General Studies, December 2011\r\n\r\n## RELEVANT COURSES:\r\n \r\n* Advanced Programming (Java)\r\n* Advanced Database (Oracle 11g)\r\n* Software Development\r\n* Digital Media\r\n* Principles of Management\r\n* Operating Systems \r\n\r\n## SKILLS\r\n \r\n* Java/Android\r\n* SQL\r\n* Microsoft Office Suite\r\n* Microsoft Windows 7, Vista, XP\r\n \r\n\r\n\r\n## PROFESSIONAL EXPERIENCE\r\n\r\n \r\nGwinnett Medical Center, Lawrenceville, GA\t\t\t\t\t 3/2014 – Present\r\nPC Tech Intern\r\n\r\nSynergy Benefits, Atlanta, GA\t\t\t\t\t\t\t 9/2010 – 12/2013\r\nBilling & Enrollment Specialist\r\n\r\nWillis, Lawrenceville, GA\t\t\t\t\t\t\t 7/2009-9/2010\r\nAccount Executive/Market Analyst\r\n\r\nHR Outsourcing, Lawrenceville, GA\t\t\t\t\t\t 8/2008-3/2009\r\nBenefits Specialist\r\n\r\nHRH, Lawrenceville, GA\t\t\t\t\t\t\t            \t 7/2007-7/2008\r\nAccount Executive/Market Analyst\r\n\r\nOffice Depot Business Solutions Division, Norcross, GA\t\t            \t            \t3/2006 – 7/2007\r\nSales Assistant\r\n \r\n\r\n## MEMBERSHIPS\r\n\r\n* Upsilon Pi Epsilon (IT Honors Society)\r\n* Association of Information Technology Professionals (AITP)\r\n\r\n","google":"","note":"Don't delete this file! It's used internally to help with page regeneration."}